{
  "timestamp": 1774917173572,
  "throughYear": 2025,
  "totals": {
    "commits": 223,
    "issues": 1,
    "prs": 51
  },
  "yearly": {
    "2014": {
      "commits": 0,
      "issues": 0,
      "prs": 0
    },
    "2015": {
      "commits": 0,
      "issues": 0,
      "prs": 0
    },
    "2016": {
      "commits": 0,
      "issues": 0,
      "prs": 0
    },
    "2017": {
      "commits": 0,
      "issues": 0,
      "prs": 0
    },
    "2018": {
      "commits": 0,
      "issues": 0,
      "prs": 0
    },
    "2019": {
      "commits": 0,
      "issues": 1,
      "prs": 0
    },
    "2020": {
      "commits": 0,
      "issues": 0,
      "prs": 0
    },
    "2021": {
      "commits": 49,
      "issues": 0,
      "prs": 4
    },
    "2022": {
      "commits": 8,
      "issues": 0,
      "prs": 0
    },
    "2023": {
      "commits": 3,
      "issues": 0,
      "prs": 0
    },
    "2024": {
      "commits": 19,
      "issues": 0,
      "prs": 0
    },
    "2025": {
      "commits": 2,
      "issues": 0,
      "prs": 0
    }
  }
}